{
  "This Week Statistics": "Статистика Цього Тижня",
  "this year": "цього року",
  "You made an extra": "Зароблено додатковo",
  "Week": "Тиждень",
  "Month": "Місяць",
  "Total Sales": "Всього Продаж",
  "Total Order": "Всього Замовлень",
  "Total Users": "Всього Користувачів",
  "Total Page Views": "Загальні Перегляди Сторінок",
  "Analytics Report": "Аналітичний Звіт",
  "Recent Orders": "Останні Замовлення",
  "Income Overview": "Огляд Прибутку",
  "Unique Visitor": "Унікальні Відвідувачі",
  "Please, Login": "Увійдіть",
  "Login": "Увійти",
  "Donʼt have an account?": "Ще немає аккаунту?",
  "Email Address": "Почтова Адреса",
  "Password": "Пароль",
  "Forgot Password?": "Забули Пароль?",
  "Keep me sign in": "Запамʼятати мене",
  "Login with": "Увійти за допомогою",
  "Profile": "Профіль"
}
